odoo10_addon_l10n_it_intrastat_statement-10.0.1.1.4-py3.8-nspkg.pth
odoo/addons/l10n_it_intrastat_statement/README.rst
odoo/addons/l10n_it_intrastat_statement/__init__.py
odoo/addons/l10n_it_intrastat_statement/__manifest__.py
odoo/addons/l10n_it_intrastat_statement/data/sequence.xml
odoo/addons/l10n_it_intrastat_statement/i18n/es.po
odoo/addons/l10n_it_intrastat_statement/i18n/it.po
odoo/addons/l10n_it_intrastat_statement/i18n/l10n_it_intrastat_statement.pot
odoo/addons/l10n_it_intrastat_statement/models/__init__.py
odoo/addons/l10n_it_intrastat_statement/models/config.py
odoo/addons/l10n_it_intrastat_statement/models/intrastat_statement.py
odoo/addons/l10n_it_intrastat_statement/models/intrastat_statement_purchase_section.py
odoo/addons/l10n_it_intrastat_statement/models/intrastat_statement_sale_section.py
odoo/addons/l10n_it_intrastat_statement/models/intrastat_statement_section.py
odoo/addons/l10n_it_intrastat_statement/readme/CONTRIBUTORS.rst
odoo/addons/l10n_it_intrastat_statement/readme/DESCRIPTION.rst
odoo/addons/l10n_it_intrastat_statement/readme/USAGE.rst
odoo/addons/l10n_it_intrastat_statement/report/intrastat_mod1_bis.xml
odoo/addons/l10n_it_intrastat_statement/report/intrastat_mod1_ter.xml
odoo/addons/l10n_it_intrastat_statement/report/report_intrastat_mod1.xml
odoo/addons/l10n_it_intrastat_statement/report/report_intrastat_mod2.xml
odoo/addons/l10n_it_intrastat_statement/report/report_intrastat_mod2_bis.xml
odoo/addons/l10n_it_intrastat_statement/report/reports.xml
odoo/addons/l10n_it_intrastat_statement/security/ir.model.access.csv
odoo/addons/l10n_it_intrastat_statement/security/rules.xml
odoo/addons/l10n_it_intrastat_statement/static/description/icon.png
odoo/addons/l10n_it_intrastat_statement/static/description/index.html
odoo/addons/l10n_it_intrastat_statement/static/img/agenzia_dogane.jpg
odoo/addons/l10n_it_intrastat_statement/static/img/logo_dogane.gif
odoo/addons/l10n_it_intrastat_statement/tests/__init__.py
odoo10_addon_l10n_it_intrastat_statement-10.0.1.1.4.dist-info/METADATA
odoo10_addon_l10n_it_intrastat_statement-10.0.1.1.4.dist-info/WHEEL
odoo10_addon_l10n_it_intrastat_statement-10.0.1.1.4.dist-info/namespace_packages.txt
odoo10_addon_l10n_it_intrastat_statement-10.0.1.1.4.dist-info/top_level.txt
odoo10_addon_l10n_it_intrastat_statement-10.0.1.1.4.dist-info/RECORD
