Metadata-Version: 2.1
Name: odoo10-addon-l10n-it-intrastat-statement
Version: 10.0.1.1.4
Summary: Dichiarazione Intrastat per l'Agenzia delle Dogane
Home-page: https://github.com/OCA/l10n-italy/tree/10.0/l10n_it_intrastat_statement
Author: Openforce, Link IT srl, Agile Business Group, Odoo Community Association (OCA)
Author-email: support@odoo-community.org
License: AGPL-3
Platform: UNKNOWN
Classifier: Programming Language :: Python
Classifier: Framework :: Odoo
Classifier: License :: OSI Approved :: GNU Affero General Public License v3
Requires-Python: ~=2.7
Requires-Dist: odoo10-addon-l10n-it-intrastat
Requires-Dist: odoo (<10.1dev,>=10.0)
